<?xml version="1.0" ?>
<annotation>
  <folder>aws_amazon_route_53</folder>
  <filename>aws_amazon_route_53_0002.png</filename>
  <size>
    <width>4445</width>
    <height>2444</height>
    <depth>3</depth>
  </size>
  <segmented>0</segmented>
  <object>
    <name>aws_amazon_route_53</name>
    <pose>Unspecified</pose>
    <truncated>0</truncated>
    <difficult>0</difficult>
    <bndbox>
      <xmin>2437</xmin>
      <ymin>1956</ymin>
      <xmax>2569</xmax>
      <ymax>2088</ymax>
    </bndbox>
  </object>
  <object>
    <name>aws_ec2_instances</name>
    <pose>Unspecified</pose>
    <truncated>0</truncated>
    <difficult>0</difficult>
    <bndbox>
      <xmin>2831</xmin>
      <ymin>1436</ymin>
      <xmax>2967</xmax>
      <ymax>1572</ymax>
    </bndbox>
  </object>
  <object>
    <name>aws_cloudformation</name>
    <pose>Unspecified</pose>
    <truncated>0</truncated>
    <difficult>0</difficult>
    <bndbox>
      <xmin>1887</xmin>
      <ymin>834</ymin>
      <xmax>2021</xmax>
      <ymax>968</ymax>
    </bndbox>
  </object>
  <object>
    <name>aws_amazon_api_gateway</name>
    <pose>Unspecified</pose>
    <truncated>0</truncated>
    <difficult>0</difficult>
    <bndbox>
      <xmin>1207</xmin>
      <ymin>1275</ymin>
      <xmax>1337</xmax>
      <ymax>1405</ymax>
    </bndbox>
  </object>
  <object>
    <name>aws_identity_and_access_management</name>
    <pose>Unspecified</pose>
    <truncated>0</truncated>
    <difficult>0</difficult>
    <bndbox>
      <xmin>919</xmin>
      <ymin>1835</ymin>
      <xmax>1051</xmax>
      <ymax>1967</ymax>
    </bndbox>
  </object>
  <object>
    <name>aws_aurora_amazon_rds_instance</name>
    <pose>Unspecified</pose>
    <truncated>0</truncated>
    <difficult>0</difficult>
    <bndbox>
      <xmin>3061</xmin>
      <ymin>609</ymin>
      <xmax>3127</xmax>
      <ymax>675</ymax>
    </bndbox>
  </object>
  <object>
    <name>aws_amazon_dynamodb</name>
    <pose>Unspecified</pose>
    <truncated>0</truncated>
    <difficult>0</difficult>
    <bndbox>
      <xmin>573</xmin>
      <ymin>326</ymin>
      <xmax>705</xmax>
      <ymax>458</ymax>
    </bndbox>
  </object>
</annotation>
