<?xml version="1.0" ?>
<annotation>
  <folder>gcp_vertex_ai</folder>
  <filename>gcp_vertex_ai_0007.png</filename>
  <size>
    <width>886</width>
    <height>590</height>
    <depth>3</depth>
  </size>
  <segmented>0</segmented>
  <object>
    <name>gcp_vertex_ai</name>
    <pose>Unspecified</pose>
    <truncated>0</truncated>
    <difficult>0</difficult>
    <bndbox>
      <xmin>241</xmin>
      <ymin>413</ymin>
      <xmax>371</xmax>
      <ymax>543</ymax>
    </bndbox>
  </object>
  <object>
    <name>gcp_google_kubernetes_engine</name>
    <pose>Unspecified</pose>
    <truncated>0</truncated>
    <difficult>0</difficult>
    <bndbox>
      <xmin>662</xmin>
      <ymin>191</ymin>
      <xmax>764</xmax>
      <ymax>293</ymax>
    </bndbox>
  </object>
  <object>
    <name>aws_amazon_rds</name>
    <pose>Unspecified</pose>
    <truncated>0</truncated>
    <difficult>0</difficult>
    <bndbox>
      <xmin>684</xmin>
      <ymin>296</ymin>
      <xmax>786</xmax>
      <ymax>398</ymax>
    </bndbox>
  </object>
  <object>
    <name>azure_cosmos_db</name>
    <pose>Unspecified</pose>
    <truncated>0</truncated>
    <difficult>0</difficult>
    <bndbox>
      <xmin>696</xmin>
      <ymin>74</ymin>
      <xmax>794</xmax>
      <ymax>172</ymax>
    </bndbox>
  </object>
  <object>
    <name>aws_elastic_container_service_service</name>
    <pose>Unspecified</pose>
    <truncated>0</truncated>
    <difficult>0</difficult>
    <bndbox>
      <xmin>232</xmin>
      <ymin>59</ymin>
      <xmax>368</xmax>
      <ymax>195</ymax>
    </bndbox>
  </object>
  <object>
    <name>aws_amazon_cloudfront</name>
    <pose>Unspecified</pose>
    <truncated>0</truncated>
    <difficult>0</difficult>
    <bndbox>
      <xmin>437</xmin>
      <ymin>76</ymin>
      <xmax>503</xmax>
      <ymax>142</ymax>
    </bndbox>
  </object>
  <object>
    <name>aws_cloudformation</name>
    <pose>Unspecified</pose>
    <truncated>0</truncated>
    <difficult>0</difficult>
    <bndbox>
      <xmin>517</xmin>
      <ymin>59</ymin>
      <xmax>655</xmax>
      <ymax>197</ymax>
    </bndbox>
  </object>
  <object>
    <name>gcp_cloud_run</name>
    <pose>Unspecified</pose>
    <truncated>0</truncated>
    <difficult>0</difficult>
    <bndbox>
      <xmin>540</xmin>
      <ymin>196</ymin>
      <xmax>606</xmax>
      <ymax>262</ymax>
    </bndbox>
  </object>
  <object>
    <name>aws_amazon_simple_queue_service</name>
    <pose>Unspecified</pose>
    <truncated>0</truncated>
    <difficult>0</difficult>
    <bndbox>
      <xmin>380</xmin>
      <ymin>316</ymin>
      <xmax>450</xmax>
      <ymax>386</ymax>
    </bndbox>
  </object>
  <object>
    <name>aws_simple_storage_service_bucket_with_objects</name>
    <pose>Unspecified</pose>
    <truncated>0</truncated>
    <difficult>0</difficult>
    <bndbox>
      <xmin>248</xmin>
      <ymin>311</ymin>
      <xmax>350</xmax>
      <ymax>413</ymax>
    </bndbox>
  </object>
  <object>
    <name>azure_vm_scale_sets</name>
    <pose>Unspecified</pose>
    <truncated>0</truncated>
    <difficult>0</difficult>
    <bndbox>
      <xmin>96</xmin>
      <ymin>177</ymin>
      <xmax>228</xmax>
      <ymax>309</ymax>
    </bndbox>
  </object>
</annotation>
