<?xml version="1.0" ?>
<annotation>
  <folder>azure_logic_apps</folder>
  <filename>azure_logic_apps_0006.png</filename>
  <size>
    <width>4819</width>
    <height>2408</height>
    <depth>3</depth>
  </size>
  <segmented>0</segmented>
  <object>
    <name>azure_logic_apps</name>
    <pose>Unspecified</pose>
    <truncated>0</truncated>
    <difficult>0</difficult>
    <bndbox>
      <xmin>696</xmin>
      <ymin>1712</ymin>
      <xmax>766</xmax>
      <ymax>1782</ymax>
    </bndbox>
  </object>
  <object>
    <name>aws_identity_access_management_role</name>
    <pose>Unspecified</pose>
    <truncated>0</truncated>
    <difficult>0</difficult>
    <bndbox>
      <xmin>4192</xmin>
      <ymin>2080</ymin>
      <xmax>4258</xmax>
      <ymax>2146</ymax>
    </bndbox>
  </object>
  <object>
    <name>azure_load_balancers</name>
    <pose>Unspecified</pose>
    <truncated>0</truncated>
    <difficult>0</difficult>
    <bndbox>
      <xmin>3995</xmin>
      <ymin>527</ymin>
      <xmax>4133</xmax>
      <ymax>665</ymax>
    </bndbox>
  </object>
  <object>
    <name>aws_vpc_virtual_private_cloud_vpc</name>
    <pose>Unspecified</pose>
    <truncated>0</truncated>
    <difficult>0</difficult>
    <bndbox>
      <xmin>3405</xmin>
      <ymin>955</ymin>
      <xmax>3509</xmax>
      <ymax>1059</ymax>
    </bndbox>
  </object>
  <object>
    <name>azure_virtual_machine</name>
    <pose>Unspecified</pose>
    <truncated>0</truncated>
    <difficult>0</difficult>
    <bndbox>
      <xmin>4154</xmin>
      <ymin>1441</ymin>
      <xmax>4252</xmax>
      <ymax>1539</ymax>
    </bndbox>
  </object>
  <object>
    <name>aws_elastic_load_balancing_application_load_balancer</name>
    <pose>Unspecified</pose>
    <truncated>0</truncated>
    <difficult>0</difficult>
    <bndbox>
      <xmin>2127</xmin>
      <ymin>1512</ymin>
      <xmax>2265</xmax>
      <ymax>1650</ymax>
    </bndbox>
  </object>
  <object>
    <name>gcp_cloud_sql</name>
    <pose>Unspecified</pose>
    <truncated>0</truncated>
    <difficult>0</difficult>
    <bndbox>
      <xmin>2648</xmin>
      <ymin>1955</ymin>
      <xmax>2782</xmax>
      <ymax>2089</ymax>
    </bndbox>
  </object>
  <object>
    <name>azure_data_factories</name>
    <pose>Unspecified</pose>
    <truncated>0</truncated>
    <difficult>0</difficult>
    <bndbox>
      <xmin>1514</xmin>
      <ymin>1096</ymin>
      <xmax>1614</xmax>
      <ymax>1196</ymax>
    </bndbox>
  </object>
  <object>
    <name>gcp_vertex_ai</name>
    <pose>Unspecified</pose>
    <truncated>0</truncated>
    <difficult>0</difficult>
    <bndbox>
      <xmin>1671</xmin>
      <ymin>394</ymin>
      <xmax>1775</xmax>
      <ymax>498</ymax>
    </bndbox>
  </object>
  <object>
    <name>aws_amazon_cloudwatch</name>
    <pose>Unspecified</pose>
    <truncated>0</truncated>
    <difficult>0</difficult>
    <bndbox>
      <xmin>1899</xmin>
      <ymin>1887</ymin>
      <xmax>1997</xmax>
      <ymax>1985</ymax>
    </bndbox>
  </object>
</annotation>
