<?xml version="1.0" ?>
<annotation>
  <folder>aws_cloudformation_template</folder>
  <filename>aws_cloudformation_template_0001.png</filename>
  <size>
    <width>1200</width>
    <height>800</height>
    <depth>3</depth>
  </size>
  <segmented>0</segmented>
  <object>
    <name>aws_cloudformation_template</name>
    <pose>Unspecified</pose>
    <truncated>0</truncated>
    <difficult>0</difficult>
    <bndbox>
      <xmin>697</xmin>
      <ymin>139</ymin>
      <xmax>797</xmax>
      <ymax>239</ymax>
    </bndbox>
  </object>
  <object>
    <name>azure_resource_groups</name>
    <pose>Unspecified</pose>
    <truncated>0</truncated>
    <difficult>0</difficult>
    <bndbox>
      <xmin>585</xmin>
      <ymin>465</ymin>
      <xmax>653</xmax>
      <ymax>533</ymax>
    </bndbox>
  </object>
  <object>
    <name>aws_lambda</name>
    <pose>Unspecified</pose>
    <truncated>0</truncated>
    <difficult>0</difficult>
    <bndbox>
      <xmin>193</xmin>
      <ymin>81</ymin>
      <xmax>297</xmax>
      <ymax>185</ymax>
    </bndbox>
  </object>
  <object>
    <name>azure_logic_apps</name>
    <pose>Unspecified</pose>
    <truncated>0</truncated>
    <difficult>0</difficult>
    <bndbox>
      <xmin>184</xmin>
      <ymin>616</ymin>
      <xmax>286</xmax>
      <ymax>718</ymax>
    </bndbox>
  </object>
  <object>
    <name>gcp_compute_engine</name>
    <pose>Unspecified</pose>
    <truncated>0</truncated>
    <difficult>0</difficult>
    <bndbox>
      <xmin>358</xmin>
      <ymin>265</ymin>
      <xmax>488</xmax>
      <ymax>395</ymax>
    </bndbox>
  </object>
  <object>
    <name>aws_simple_storage_service_object</name>
    <pose>Unspecified</pose>
    <truncated>0</truncated>
    <difficult>0</difficult>
    <bndbox>
      <xmin>361</xmin>
      <ymin>414</ymin>
      <xmax>463</xmax>
      <ymax>516</ymax>
    </bndbox>
  </object>
  <object>
    <name>azure_key_vaults</name>
    <pose>Unspecified</pose>
    <truncated>0</truncated>
    <difficult>0</difficult>
    <bndbox>
      <xmin>313</xmin>
      <ymin>569</ymin>
      <xmax>453</xmax>
      <ymax>709</ymax>
    </bndbox>
  </object>
  <object>
    <name>azure_sql</name>
    <pose>Unspecified</pose>
    <truncated>0</truncated>
    <difficult>0</difficult>
    <bndbox>
      <xmin>559</xmin>
      <ymin>97</ymin>
      <xmax>625</xmax>
      <ymax>163</ymax>
    </bndbox>
  </object>
  <object>
    <name>aws_elastic_load_balancing_network_load_balancer</name>
    <pose>Unspecified</pose>
    <truncated>0</truncated>
    <difficult>0</difficult>
    <bndbox>
      <xmin>713</xmin>
      <ymin>410</ymin>
      <xmax>815</xmax>
      <ymax>512</ymax>
    </bndbox>
  </object>
  <object>
    <name>aws_aurora_amazon_rds_instance</name>
    <pose>Unspecified</pose>
    <truncated>0</truncated>
    <difficult>0</difficult>
    <bndbox>
      <xmin>397</xmin>
      <ymin>87</ymin>
      <xmax>499</xmax>
      <ymax>189</ymax>
    </bndbox>
  </object>
  <object>
    <name>aws_simple_notification_service_topic</name>
    <pose>Unspecified</pose>
    <truncated>0</truncated>
    <difficult>0</difficult>
    <bndbox>
      <xmin>540</xmin>
      <ymin>259</ymin>
      <xmax>644</xmax>
      <ymax>363</ymax>
    </bndbox>
  </object>
  <object>
    <name>azure_event_hubs</name>
    <pose>Unspecified</pose>
    <truncated>0</truncated>
    <difficult>0</difficult>
    <bndbox>
      <xmin>889</xmin>
      <ymin>113</ymin>
      <xmax>993</xmax>
      <ymax>217</ymax>
    </bndbox>
  </object>
  <object>
    <name>aws_amazon_rds</name>
    <pose>Unspecified</pose>
    <truncated>0</truncated>
    <difficult>0</difficult>
    <bndbox>
      <xmin>143</xmin>
      <ymin>246</ymin>
      <xmax>245</xmax>
      <ymax>348</ymax>
    </bndbox>
  </object>
</annotation>
