<?xml version="1.0" ?>
<annotation>
  <folder>azure_resource_groups</folder>
  <filename>azure_resource_groups_0003.png</filename>
  <size>
    <width>831</width>
    <height>601</height>
    <depth>3</depth>
  </size>
  <segmented>0</segmented>
  <object>
    <name>azure_resource_groups</name>
    <pose>Unspecified</pose>
    <truncated>0</truncated>
    <difficult>0</difficult>
    <bndbox>
      <xmin>624</xmin>
      <ymin>300</ymin>
      <xmax>728</xmax>
      <ymax>404</ymax>
    </bndbox>
  </object>
  <object>
    <name>aws_key_management_service</name>
    <pose>Unspecified</pose>
    <truncated>0</truncated>
    <difficult>0</difficult>
    <bndbox>
      <xmin>351</xmin>
      <ymin>420</ymin>
      <xmax>449</xmax>
      <ymax>518</ymax>
    </bndbox>
  </object>
  <object>
    <name>azure_sql_managed_instance</name>
    <pose>Unspecified</pose>
    <truncated>0</truncated>
    <difficult>0</difficult>
    <bndbox>
      <xmin>530</xmin>
      <ymin>85</ymin>
      <xmax>598</xmax>
      <ymax>153</ymax>
    </bndbox>
  </object>
  <object>
    <name>gcp_vertex_ai</name>
    <pose>Unspecified</pose>
    <truncated>0</truncated>
    <difficult>0</difficult>
    <bndbox>
      <xmin>619</xmin>
      <ymin>63</ymin>
      <xmax>717</xmax>
      <ymax>161</ymax>
    </bndbox>
  </object>
  <object>
    <name>azure_sql_database</name>
    <pose>Unspecified</pose>
    <truncated>0</truncated>
    <difficult>0</difficult>
    <bndbox>
      <xmin>368</xmin>
      <ymin>86</ymin>
      <xmax>434</xmax>
      <ymax>152</ymax>
    </bndbox>
  </object>
  <object>
    <name>aws_identity_access_management_role</name>
    <pose>Unspecified</pose>
    <truncated>0</truncated>
    <difficult>0</difficult>
    <bndbox>
      <xmin>647</xmin>
      <ymin>189</ymin>
      <xmax>745</xmax>
      <ymax>287</ymax>
    </bndbox>
  </object>
  <object>
    <name>aws_cloudformation</name>
    <pose>Unspecified</pose>
    <truncated>0</truncated>
    <difficult>0</difficult>
    <bndbox>
      <xmin>349</xmin>
      <ymin>300</ymin>
      <xmax>479</xmax>
      <ymax>430</ymax>
    </bndbox>
  </object>
  <object>
    <name>azure_machine_learning_studio_workspaces</name>
    <pose>Unspecified</pose>
    <truncated>0</truncated>
    <difficult>0</difficult>
    <bndbox>
      <xmin>616</xmin>
      <ymin>429</ymin>
      <xmax>686</xmax>
      <ymax>499</ymax>
    </bndbox>
  </object>
  <object>
    <name>aws_lambda</name>
    <pose>Unspecified</pose>
    <truncated>0</truncated>
    <difficult>0</difficult>
    <bndbox>
      <xmin>85</xmin>
      <ymin>421</ymin>
      <xmax>187</xmax>
      <ymax>523</ymax>
    </bndbox>
  </object>
  <object>
    <name>gcp_identity_and_access_management</name>
    <pose>Unspecified</pose>
    <truncated>0</truncated>
    <difficult>0</difficult>
    <bndbox>
      <xmin>500</xmin>
      <ymin>304</ymin>
      <xmax>604</xmax>
      <ymax>408</ymax>
    </bndbox>
  </object>
</annotation>
