<?xml version="1.0" ?>
<annotation>
  <folder>aws_elastic_block_store_volume</folder>
  <filename>aws_elastic_block_store_volume_0001.png</filename>
  <size>
    <width>4238</width>
    <height>2878</height>
    <depth>3</depth>
  </size>
  <segmented>0</segmented>
  <object>
    <name>aws_elastic_block_store_volume</name>
    <pose>Unspecified</pose>
    <truncated>0</truncated>
    <difficult>0</difficult>
    <bndbox>
      <xmin>1469</xmin>
      <ymin>357</ymin>
      <xmax>1537</xmax>
      <ymax>425</ymax>
    </bndbox>
  </object>
  <object>
    <name>azure_event_hubs</name>
    <pose>Unspecified</pose>
    <truncated>0</truncated>
    <difficult>0</difficult>
    <bndbox>
      <xmin>2530</xmin>
      <ymin>1106</ymin>
      <xmax>2598</xmax>
      <ymax>1174</ymax>
    </bndbox>
  </object>
  <object>
    <name>azure_api_management_services</name>
    <pose>Unspecified</pose>
    <truncated>0</truncated>
    <difficult>0</difficult>
    <bndbox>
      <xmin>1302</xmin>
      <ymin>1214</ymin>
      <xmax>1370</xmax>
      <ymax>1282</ymax>
    </bndbox>
  </object>
  <object>
    <name>azure_app_services</name>
    <pose>Unspecified</pose>
    <truncated>0</truncated>
    <difficult>0</difficult>
    <bndbox>
      <xmin>1995</xmin>
      <ymin>2135</ymin>
      <xmax>2097</xmax>
      <ymax>2237</ymax>
    </bndbox>
  </object>
  <object>
    <name>aws_ec2_instances</name>
    <pose>Unspecified</pose>
    <truncated>0</truncated>
    <difficult>0</difficult>
    <bndbox>
      <xmin>3191</xmin>
      <ymin>454</ymin>
      <xmax>3289</xmax>
      <ymax>552</ymax>
    </bndbox>
  </object>
  <object>
    <name>azure_load_balancers</name>
    <pose>Unspecified</pose>
    <truncated>0</truncated>
    <difficult>0</difficult>
    <bndbox>
      <xmin>1029</xmin>
      <ymin>2036</ymin>
      <xmax>1095</xmax>
      <ymax>2102</ymax>
    </bndbox>
  </object>
</annotation>
