<?xml version="1.0" ?>
<annotation>
  <folder>gcp_cloud_load_balancing</folder>
  <filename>gcp_cloud_load_balancing_0001.png</filename>
  <size>
    <width>1323</width>
    <height>882</height>
    <depth>3</depth>
  </size>
  <segmented>0</segmented>
  <object>
    <name>gcp_cloud_load_balancing</name>
    <pose>Unspecified</pose>
    <truncated>0</truncated>
    <difficult>0</difficult>
    <bndbox>
      <xmin>559</xmin>
      <ymin>345</ymin>
      <xmax>627</xmax>
      <ymax>413</ymax>
    </bndbox>
  </object>
  <object>
    <name>aws_cloudformation</name>
    <pose>Unspecified</pose>
    <truncated>0</truncated>
    <difficult>0</difficult>
    <bndbox>
      <xmin>452</xmin>
      <ymin>661</ymin>
      <xmax>552</xmax>
      <ymax>761</ymax>
    </bndbox>
  </object>
  <object>
    <name>aws_aurora_amazon_rds_instance</name>
    <pose>Unspecified</pose>
    <truncated>0</truncated>
    <difficult>0</difficult>
    <bndbox>
      <xmin>158</xmin>
      <ymin>445</ymin>
      <xmax>256</xmax>
      <ymax>543</ymax>
    </bndbox>
  </object>
  <object>
    <name>aws_simple_storage_service_object</name>
    <pose>Unspecified</pose>
    <truncated>0</truncated>
    <difficult>0</difficult>
    <bndbox>
      <xmin>597</xmin>
      <ymin>440</ymin>
      <xmax>733</xmax>
      <ymax>576</ymax>
    </bndbox>
  </object>
  <object>
    <name>gcp_virtual_private_cloud</name>
    <pose>Unspecified</pose>
    <truncated>0</truncated>
    <difficult>0</difficult>
    <bndbox>
      <xmin>779</xmin>
      <ymin>462</ymin>
      <xmax>909</xmax>
      <ymax>592</ymax>
    </bndbox>
  </object>
  <object>
    <name>aws_cloudformation_template</name>
    <pose>Unspecified</pose>
    <truncated>0</truncated>
    <difficult>0</difficult>
    <bndbox>
      <xmin>1003</xmin>
      <ymin>165</ymin>
      <xmax>1069</xmax>
      <ymax>231</ymax>
    </bndbox>
  </object>
  <object>
    <name>aws_simple_storage_service_s3_standard</name>
    <pose>Unspecified</pose>
    <truncated>0</truncated>
    <difficult>0</difficult>
    <bndbox>
      <xmin>369</xmin>
      <ymin>475</ymin>
      <xmax>507</xmax>
      <ymax>613</ymax>
    </bndbox>
  </object>
  <object>
    <name>aws_amazon_rds</name>
    <pose>Unspecified</pose>
    <truncated>0</truncated>
    <difficult>0</difficult>
    <bndbox>
      <xmin>163</xmin>
      <ymin>639</ymin>
      <xmax>267</xmax>
      <ymax>743</ymax>
    </bndbox>
  </object>
  <object>
    <name>gcp_cloud_run</name>
    <pose>Unspecified</pose>
    <truncated>0</truncated>
    <difficult>0</difficult>
    <bndbox>
      <xmin>380</xmin>
      <ymin>128</ymin>
      <xmax>482</xmax>
      <ymax>230</ymax>
    </bndbox>
  </object>
</annotation>
