<?xml version="1.0" ?>
<annotation>
  <folder>aws_amazon_cloudfront</folder>
  <filename>aws_amazon_cloudfront_0002.png</filename>
  <size>
    <width>2916</width>
    <height>2316</height>
    <depth>3</depth>
  </size>
  <segmented>0</segmented>
  <object>
    <name>aws_amazon_cloudfront</name>
    <pose>Unspecified</pose>
    <truncated>0</truncated>
    <difficult>0</difficult>
    <bndbox>
      <xmin>461</xmin>
      <ymin>316</ymin>
      <xmax>593</xmax>
      <ymax>448</ymax>
    </bndbox>
  </object>
  <object>
    <name>aws_amazon_elastic_container_service</name>
    <pose>Unspecified</pose>
    <truncated>0</truncated>
    <difficult>0</difficult>
    <bndbox>
      <xmin>426</xmin>
      <ymin>842</ymin>
      <xmax>556</xmax>
      <ymax>972</ymax>
    </bndbox>
  </object>
  <object>
    <name>aws_simple_queue_service_queue</name>
    <pose>Unspecified</pose>
    <truncated>0</truncated>
    <difficult>0</difficult>
    <bndbox>
      <xmin>1013</xmin>
      <ymin>1235</ymin>
      <xmax>1149</xmax>
      <ymax>1371</ymax>
    </bndbox>
  </object>
  <object>
    <name>aws_amazon_elastic_kubernetes_service</name>
    <pose>Unspecified</pose>
    <truncated>0</truncated>
    <difficult>0</difficult>
    <bndbox>
      <xmin>1936</xmin>
      <ymin>377</ymin>
      <xmax>2004</xmax>
      <ymax>445</ymax>
    </bndbox>
  </object>
  <object>
    <name>aws_amazon_ec2_auto_scaling</name>
    <pose>Unspecified</pose>
    <truncated>0</truncated>
    <difficult>0</difficult>
    <bndbox>
      <xmin>1320</xmin>
      <ymin>773</ymin>
      <xmax>1420</xmax>
      <ymax>873</ymax>
    </bndbox>
  </object>
  <object>
    <name>azure_devops</name>
    <pose>Unspecified</pose>
    <truncated>0</truncated>
    <difficult>0</difficult>
    <bndbox>
      <xmin>1153</xmin>
      <ymin>960</ymin>
      <xmax>1219</xmax>
      <ymax>1026</ymax>
    </bndbox>
  </object>
  <object>
    <name>aws_elastic_load_balancing_application_load_balancer</name>
    <pose>Unspecified</pose>
    <truncated>0</truncated>
    <difficult>0</difficult>
    <bndbox>
      <xmin>1996</xmin>
      <ymin>720</ymin>
      <xmax>2094</xmax>
      <ymax>818</ymax>
    </bndbox>
  </object>
  <object>
    <name>azure_cosmos_db</name>
    <pose>Unspecified</pose>
    <truncated>0</truncated>
    <difficult>0</difficult>
    <bndbox>
      <xmin>1844</xmin>
      <ymin>1342</ymin>
      <xmax>1946</xmax>
      <ymax>1444</ymax>
    </bndbox>
  </object>
  <object>
    <name>azure_machine_learning</name>
    <pose>Unspecified</pose>
    <truncated>0</truncated>
    <difficult>0</difficult>
    <bndbox>
      <xmin>854</xmin>
      <ymin>1673</ymin>
      <xmax>922</xmax>
      <ymax>1741</ymax>
    </bndbox>
  </object>
  <object>
    <name>aws_cloudformation_template</name>
    <pose>Unspecified</pose>
    <truncated>0</truncated>
    <difficult>0</difficult>
    <bndbox>
      <xmin>2224</xmin>
      <ymin>534</ymin>
      <xmax>2324</xmax>
      <ymax>634</ymax>
    </bndbox>
  </object>
  <object>
    <name>azure_synapse_analytics</name>
    <pose>Unspecified</pose>
    <truncated>0</truncated>
    <difficult>0</difficult>
    <bndbox>
      <xmin>2542</xmin>
      <ymin>1981</ymin>
      <xmax>2612</xmax>
      <ymax>2051</ymax>
    </bndbox>
  </object>
  <object>
    <name>aws_amazon_simple_queue_service</name>
    <pose>Unspecified</pose>
    <truncated>0</truncated>
    <difficult>0</difficult>
    <bndbox>
      <xmin>1564</xmin>
      <ymin>1723</ymin>
      <xmax>1630</xmax>
      <ymax>1789</ymax>
    </bndbox>
  </object>
  <object>
    <name>aws_simple_storage_service_object</name>
    <pose>Unspecified</pose>
    <truncated>0</truncated>
    <difficult>0</difficult>
    <bndbox>
      <xmin>297</xmin>
      <ymin>1364</ymin>
      <xmax>399</xmax>
      <ymax>1466</ymax>
    </bndbox>
  </object>
  <object>
    <name>azure_key_vaults</name>
    <pose>Unspecified</pose>
    <truncated>0</truncated>
    <difficult>0</difficult>
    <bndbox>
      <xmin>801</xmin>
      <ymin>335</ymin>
      <xmax>905</xmax>
      <ymax>439</ymax>
    </bndbox>
  </object>
  <object>
    <name>aws_amazon_virtual_private_cloud</name>
    <pose>Unspecified</pose>
    <truncated>0</truncated>
    <difficult>0</difficult>
    <bndbox>
      <xmin>2355</xmin>
      <ymin>1541</ymin>
      <xmax>2425</xmax>
      <ymax>1611</ymax>
    </bndbox>
  </object>
</annotation>
