<?xml version="1.0" ?>
<annotation>
  <folder>aws_route_53_hosted_zone</folder>
  <filename>aws_route_53_hosted_zone_0002.png</filename>
  <size>
    <width>2916</width>
    <height>1630</height>
    <depth>3</depth>
  </size>
  <segmented>0</segmented>
  <object>
    <name>aws_route_53_hosted_zone</name>
    <pose>Unspecified</pose>
    <truncated>0</truncated>
    <difficult>0</difficult>
    <bndbox>
      <xmin>2461</xmin>
      <ymin>496</ymin>
      <xmax>2593</xmax>
      <ymax>628</ymax>
    </bndbox>
  </object>
  <object>
    <name>azure_container_instances</name>
    <pose>Unspecified</pose>
    <truncated>0</truncated>
    <difficult>0</difficult>
    <bndbox>
      <xmin>1988</xmin>
      <ymin>829</ymin>
      <xmax>2056</xmax>
      <ymax>897</ymax>
    </bndbox>
  </object>
  <object>
    <name>azure_load_balancers</name>
    <pose>Unspecified</pose>
    <truncated>0</truncated>
    <difficult>0</difficult>
    <bndbox>
      <xmin>1965</xmin>
      <ymin>176</ymin>
      <xmax>2065</xmax>
      <ymax>276</ymax>
    </bndbox>
  </object>
  <object>
    <name>aws_elastic_load_balancing_network_load_balancer</name>
    <pose>Unspecified</pose>
    <truncated>0</truncated>
    <difficult>0</difficult>
    <bndbox>
      <xmin>1415</xmin>
      <ymin>654</ymin>
      <xmax>1547</xmax>
      <ymax>786</ymax>
    </bndbox>
  </object>
  <object>
    <name>aws_simple_storage_service_bucket_with_objects</name>
    <pose>Unspecified</pose>
    <truncated>0</truncated>
    <difficult>0</difficult>
    <bndbox>
      <xmin>1371</xmin>
      <ymin>1204</ymin>
      <xmax>1507</xmax>
      <ymax>1340</ymax>
    </bndbox>
  </object>
  <object>
    <name>aws_amazon_redshift</name>
    <pose>Unspecified</pose>
    <truncated>0</truncated>
    <difficult>0</difficult>
    <bndbox>
      <xmin>864</xmin>
      <ymin>641</ymin>
      <xmax>968</xmax>
      <ymax>745</ymax>
    </bndbox>
  </object>
</annotation>
