<?xml version="1.0" ?>
<annotation>
  <folder>gcp_virtual_private_cloud</folder>
  <filename>gcp_virtual_private_cloud_0008.png</filename>
  <size>
    <width>4967</width>
    <height>1913</height>
    <depth>3</depth>
  </size>
  <segmented>0</segmented>
  <object>
    <name>gcp_virtual_private_cloud</name>
    <pose>Unspecified</pose>
    <truncated>0</truncated>
    <difficult>0</difficult>
    <bndbox>
      <xmin>4022</xmin>
      <ymin>708</ymin>
      <xmax>4122</xmax>
      <ymax>808</ymax>
    </bndbox>
  </object>
  <object>
    <name>gcp_cloud_run</name>
    <pose>Unspecified</pose>
    <truncated>0</truncated>
    <difficult>0</difficult>
    <bndbox>
      <xmin>510</xmin>
      <ymin>1218</ymin>
      <xmax>614</xmax>
      <ymax>1322</ymax>
    </bndbox>
  </object>
  <object>
    <name>aws_amazon_cloudfront</name>
    <pose>Unspecified</pose>
    <truncated>0</truncated>
    <difficult>0</difficult>
    <bndbox>
      <xmin>2199</xmin>
      <ymin>1540</ymin>
      <xmax>2267</xmax>
      <ymax>1608</ymax>
    </bndbox>
  </object>
  <object>
    <name>azure_cosmos_db</name>
    <pose>Unspecified</pose>
    <truncated>0</truncated>
    <difficult>0</difficult>
    <bndbox>
      <xmin>926</xmin>
      <ymin>219</ymin>
      <xmax>994</xmax>
      <ymax>287</ymax>
    </bndbox>
  </object>
  <object>
    <name>gcp_cloud_sql</name>
    <pose>Unspecified</pose>
    <truncated>0</truncated>
    <difficult>0</difficult>
    <bndbox>
      <xmin>1384</xmin>
      <ymin>321</ymin>
      <xmax>1454</xmax>
      <ymax>391</ymax>
    </bndbox>
  </object>
  <object>
    <name>aws_key_management_service</name>
    <pose>Unspecified</pose>
    <truncated>0</truncated>
    <difficult>0</difficult>
    <bndbox>
      <xmin>512</xmin>
      <ymin>600</ymin>
      <xmax>646</xmax>
      <ymax>734</ymax>
    </bndbox>
  </object>
  <object>
    <name>gcp_compute_engine</name>
    <pose>Unspecified</pose>
    <truncated>0</truncated>
    <difficult>0</difficult>
    <bndbox>
      <xmin>3462</xmin>
      <ymin>300</ymin>
      <xmax>3598</xmax>
      <ymax>436</ymax>
    </bndbox>
  </object>
  <object>
    <name>aws_amazon_simple_storage_service</name>
    <pose>Unspecified</pose>
    <truncated>0</truncated>
    <difficult>0</difficult>
    <bndbox>
      <xmin>1882</xmin>
      <ymin>956</ymin>
      <xmax>1950</xmax>
      <ymax>1024</ymax>
    </bndbox>
  </object>
  <object>
    <name>aws_simple_storage_service_bucket_with_objects</name>
    <pose>Unspecified</pose>
    <truncated>0</truncated>
    <difficult>0</difficult>
    <bndbox>
      <xmin>2617</xmin>
      <ymin>1098</ymin>
      <xmax>2721</xmax>
      <ymax>1202</ymax>
    </bndbox>
  </object>
  <object>
    <name>azure_container_instances</name>
    <pose>Unspecified</pose>
    <truncated>0</truncated>
    <difficult>0</difficult>
    <bndbox>
      <xmin>4026</xmin>
      <ymin>220</ymin>
      <xmax>4096</xmax>
      <ymax>290</ymax>
    </bndbox>
  </object>
  <object>
    <name>azure_sql</name>
    <pose>Unspecified</pose>
    <truncated>0</truncated>
    <difficult>0</difficult>
    <bndbox>
      <xmin>3471</xmin>
      <ymin>1384</ymin>
      <xmax>3605</xmax>
      <ymax>1518</ymax>
    </bndbox>
  </object>
  <object>
    <name>aws_ec2_instance</name>
    <pose>Unspecified</pose>
    <truncated>0</truncated>
    <difficult>0</difficult>
    <bndbox>
      <xmin>1120</xmin>
      <ymin>1381</ymin>
      <xmax>1186</xmax>
      <ymax>1447</ymax>
    </bndbox>
  </object>
  <object>
    <name>aws_lambda</name>
    <pose>Unspecified</pose>
    <truncated>0</truncated>
    <difficult>0</difficult>
    <bndbox>
      <xmin>3140</xmin>
      <ymin>760</ymin>
      <xmax>3272</xmax>
      <ymax>892</ymax>
    </bndbox>
  </object>
</annotation>
