<?xml version="1.0" ?>
<annotation>
  <folder>aws_simple_storage_service_object</folder>
  <filename>aws_simple_storage_service_object_0008.png</filename>
  <size>
    <width>1535</width>
    <height>1083</height>
    <depth>3</depth>
  </size>
  <segmented>0</segmented>
  <object>
    <name>aws_simple_storage_service_object</name>
    <pose>Unspecified</pose>
    <truncated>0</truncated>
    <difficult>0</difficult>
    <bndbox>
      <xmin>277</xmin>
      <ymin>588</ymin>
      <xmax>343</xmax>
      <ymax>654</ymax>
    </bndbox>
  </object>
  <object>
    <name>aws_amazon_rds</name>
    <pose>Unspecified</pose>
    <truncated>0</truncated>
    <difficult>0</difficult>
    <bndbox>
      <xmin>426</xmin>
      <ymin>784</ymin>
      <xmax>564</xmax>
      <ymax>922</ymax>
    </bndbox>
  </object>
  <object>
    <name>azure_firewalls</name>
    <pose>Unspecified</pose>
    <truncated>0</truncated>
    <difficult>0</difficult>
    <bndbox>
      <xmin>894</xmin>
      <ymin>383</ymin>
      <xmax>1030</xmax>
      <ymax>519</ymax>
    </bndbox>
  </object>
  <object>
    <name>aws_ec2_instance</name>
    <pose>Unspecified</pose>
    <truncated>0</truncated>
    <difficult>0</difficult>
    <bndbox>
      <xmin>660</xmin>
      <ymin>193</ymin>
      <xmax>762</xmax>
      <ymax>295</ymax>
    </bndbox>
  </object>
  <object>
    <name>gcp_virtual_private_cloud</name>
    <pose>Unspecified</pose>
    <truncated>0</truncated>
    <difficult>0</difficult>
    <bndbox>
      <xmin>458</xmin>
      <ymin>125</ymin>
      <xmax>596</xmax>
      <ymax>263</ymax>
    </bndbox>
  </object>
  <object>
    <name>aws_amazon_route_53</name>
    <pose>Unspecified</pose>
    <truncated>0</truncated>
    <difficult>0</difficult>
    <bndbox>
      <xmin>1035</xmin>
      <ymin>586</ymin>
      <xmax>1101</xmax>
      <ymax>652</ymax>
    </bndbox>
  </object>
  <object>
    <name>aws_elastic_load_balancing</name>
    <pose>Unspecified</pose>
    <truncated>0</truncated>
    <difficult>0</difficult>
    <bndbox>
      <xmin>960</xmin>
      <ymin>788</ymin>
      <xmax>1092</xmax>
      <ymax>920</ymax>
    </bndbox>
  </object>
  <object>
    <name>azure_databricks</name>
    <pose>Unspecified</pose>
    <truncated>0</truncated>
    <difficult>0</difficult>
    <bndbox>
      <xmin>702</xmin>
      <ymin>432</ymin>
      <xmax>770</xmax>
      <ymax>500</ymax>
    </bndbox>
  </object>
  <object>
    <name>aws_identity_and_access_management</name>
    <pose>Unspecified</pose>
    <truncated>0</truncated>
    <difficult>0</difficult>
    <bndbox>
      <xmin>899</xmin>
      <ymin>113</ymin>
      <xmax>999</xmax>
      <ymax>213</ymax>
    </bndbox>
  </object>
  <object>
    <name>aws_key_management_service</name>
    <pose>Unspecified</pose>
    <truncated>0</truncated>
    <difficult>0</difficult>
    <bndbox>
      <xmin>679</xmin>
      <ymin>896</ymin>
      <xmax>749</xmax>
      <ymax>966</ymax>
    </bndbox>
  </object>
  <object>
    <name>gcp_pubsub</name>
    <pose>Unspecified</pose>
    <truncated>0</truncated>
    <difficult>0</difficult>
    <bndbox>
      <xmin>1139</xmin>
      <ymin>547</ymin>
      <xmax>1207</xmax>
      <ymax>615</ymax>
    </bndbox>
  </object>
  <object>
    <name>gcp_identity_and_access_management</name>
    <pose>Unspecified</pose>
    <truncated>0</truncated>
    <difficult>0</difficult>
    <bndbox>
      <xmin>166</xmin>
      <ymin>160</ymin>
      <xmax>300</xmax>
      <ymax>294</ymax>
    </bndbox>
  </object>
  <object>
    <name>gcp_vertex_ai</name>
    <pose>Unspecified</pose>
    <truncated>0</truncated>
    <difficult>0</difficult>
    <bndbox>
      <xmin>273</xmin>
      <ymin>410</ymin>
      <xmax>377</xmax>
      <ymax>514</ymax>
    </bndbox>
  </object>
  <object>
    <name>azure_virtual_networks</name>
    <pose>Unspecified</pose>
    <truncated>0</truncated>
    <difficult>0</difficult>
    <bndbox>
      <xmin>534</xmin>
      <ymin>341</ymin>
      <xmax>638</xmax>
      <ymax>445</ymax>
    </bndbox>
  </object>
  <object>
    <name>gcp_cloud_functions</name>
    <pose>Unspecified</pose>
    <truncated>0</truncated>
    <difficult>0</difficult>
    <bndbox>
      <xmin>238</xmin>
      <ymin>864</ymin>
      <xmax>336</xmax>
      <ymax>962</ymax>
    </bndbox>
  </object>
  <object>
    <name>aws_elastic_load_balancing_network_load_balancer</name>
    <pose>Unspecified</pose>
    <truncated>0</truncated>
    <difficult>0</difficult>
    <bndbox>
      <xmin>700</xmin>
      <ymin>544</ymin>
      <xmax>836</xmax>
      <ymax>680</ymax>
    </bndbox>
  </object>
</annotation>
