<?xml version="1.0" ?>
<annotation>
  <folder>aws_elastic_load_balancing_application_load_balancer</folder>
  <filename>aws_elastic_load_balancing_application_load_balancer_0002.png</filename>
  <size>
    <width>4445</width>
    <height>2444</height>
    <depth>3</depth>
  </size>
  <segmented>0</segmented>
  <object>
    <name>aws_elastic_load_balancing_application_load_balancer</name>
    <pose>Unspecified</pose>
    <truncated>0</truncated>
    <difficult>0</difficult>
    <bndbox>
      <xmin>1448</xmin>
      <ymin>285</ymin>
      <xmax>1518</xmax>
      <ymax>355</ymax>
    </bndbox>
  </object>
  <object>
    <name>azure_devops</name>
    <pose>Unspecified</pose>
    <truncated>0</truncated>
    <difficult>0</difficult>
    <bndbox>
      <xmin>2433</xmin>
      <ymin>1987</ymin>
      <xmax>2573</xmax>
      <ymax>2127</ymax>
    </bndbox>
  </object>
  <object>
    <name>aws_cloudformation</name>
    <pose>Unspecified</pose>
    <truncated>0</truncated>
    <difficult>0</difficult>
    <bndbox>
      <xmin>3682</xmin>
      <ymin>858</ymin>
      <xmax>3750</xmax>
      <ymax>926</ymax>
    </bndbox>
  </object>
  <object>
    <name>aws_ec2_instance</name>
    <pose>Unspecified</pose>
    <truncated>0</truncated>
    <difficult>0</difficult>
    <bndbox>
      <xmin>3546</xmin>
      <ymin>1328</ymin>
      <xmax>3648</xmax>
      <ymax>1430</ymax>
    </bndbox>
  </object>
  <object>
    <name>azure_monitor</name>
    <pose>Unspecified</pose>
    <truncated>0</truncated>
    <difficult>0</difficult>
    <bndbox>
      <xmin>2631</xmin>
      <ymin>957</ymin>
      <xmax>2729</xmax>
      <ymax>1055</ymax>
    </bndbox>
  </object>
  <object>
    <name>aws_lambda_lambda_function</name>
    <pose>Unspecified</pose>
    <truncated>0</truncated>
    <difficult>0</difficult>
    <bndbox>
      <xmin>1196</xmin>
      <ymin>1852</ymin>
      <xmax>1264</xmax>
      <ymax>1920</ymax>
    </bndbox>
  </object>
  <object>
    <name>aws_key_management_service</name>
    <pose>Unspecified</pose>
    <truncated>0</truncated>
    <difficult>0</difficult>
    <bndbox>
      <xmin>2084</xmin>
      <ymin>1302</ymin>
      <xmax>2150</xmax>
      <ymax>1368</ymax>
    </bndbox>
  </object>
  <object>
    <name>aws_amazon_ec2</name>
    <pose>Unspecified</pose>
    <truncated>0</truncated>
    <difficult>0</difficult>
    <bndbox>
      <xmin>3783</xmin>
      <ymin>1820</ymin>
      <xmax>3913</xmax>
      <ymax>1950</ymax>
    </bndbox>
  </object>
  <object>
    <name>aws_amazon_cloudwatch</name>
    <pose>Unspecified</pose>
    <truncated>0</truncated>
    <difficult>0</difficult>
    <bndbox>
      <xmin>2724</xmin>
      <ymin>1857</ymin>
      <xmax>2822</xmax>
      <ymax>1955</ymax>
    </bndbox>
  </object>
</annotation>
