<?xml version="1.0" ?>
<annotation>
  <folder>aws_elastic_load_balancing_application_load_balancer</folder>
  <filename>aws_elastic_load_balancing_application_load_balancer_0006.png</filename>
  <size>
    <width>4445</width>
    <height>2444</height>
    <depth>3</depth>
  </size>
  <segmented>0</segmented>
  <object>
    <name>aws_elastic_load_balancing_application_load_balancer</name>
    <pose>Unspecified</pose>
    <truncated>0</truncated>
    <difficult>0</difficult>
    <bndbox>
      <xmin>3399</xmin>
      <ymin>1894</ymin>
      <xmax>3529</xmax>
      <ymax>2024</ymax>
    </bndbox>
  </object>
  <object>
    <name>azure_firewalls</name>
    <pose>Unspecified</pose>
    <truncated>0</truncated>
    <difficult>0</difficult>
    <bndbox>
      <xmin>1632</xmin>
      <ymin>545</ymin>
      <xmax>1698</xmax>
      <ymax>611</ymax>
    </bndbox>
  </object>
  <object>
    <name>aws_elastic_container_service_service</name>
    <pose>Unspecified</pose>
    <truncated>0</truncated>
    <difficult>0</difficult>
    <bndbox>
      <xmin>1396</xmin>
      <ymin>1083</ymin>
      <xmax>1500</xmax>
      <ymax>1187</ymax>
    </bndbox>
  </object>
  <object>
    <name>aws_amazon_elastic_block_store</name>
    <pose>Unspecified</pose>
    <truncated>0</truncated>
    <difficult>0</difficult>
    <bndbox>
      <xmin>1396</xmin>
      <ymin>1237</ymin>
      <xmax>1498</xmax>
      <ymax>1339</ymax>
    </bndbox>
  </object>
  <object>
    <name>gcp_cloud_functions</name>
    <pose>Unspecified</pose>
    <truncated>0</truncated>
    <difficult>0</difficult>
    <bndbox>
      <xmin>3137</xmin>
      <ymin>658</ymin>
      <xmax>3205</xmax>
      <ymax>726</ymax>
    </bndbox>
  </object>
  <object>
    <name>azure_function_apps</name>
    <pose>Unspecified</pose>
    <truncated>0</truncated>
    <difficult>0</difficult>
    <bndbox>
      <xmin>533</xmin>
      <ymin>1040</ymin>
      <xmax>667</xmax>
      <ymax>1174</ymax>
    </bndbox>
  </object>
  <object>
    <name>azure_monitor</name>
    <pose>Unspecified</pose>
    <truncated>0</truncated>
    <difficult>0</difficult>
    <bndbox>
      <xmin>2096</xmin>
      <ymin>1801</ymin>
      <xmax>2228</xmax>
      <ymax>1933</ymax>
    </bndbox>
  </object>
  <object>
    <name>aws_simple_notification_service_topic</name>
    <pose>Unspecified</pose>
    <truncated>0</truncated>
    <difficult>0</difficult>
    <bndbox>
      <xmin>1447</xmin>
      <ymin>1729</ymin>
      <xmax>1587</xmax>
      <ymax>1869</ymax>
    </bndbox>
  </object>
  <object>
    <name>azure_network_security_groups</name>
    <pose>Unspecified</pose>
    <truncated>0</truncated>
    <difficult>0</difficult>
    <bndbox>
      <xmin>3748</xmin>
      <ymin>1589</ymin>
      <xmax>3818</xmax>
      <ymax>1659</ymax>
    </bndbox>
  </object>
  <object>
    <name>azure_vm_scale_sets</name>
    <pose>Unspecified</pose>
    <truncated>0</truncated>
    <difficult>0</difficult>
    <bndbox>
      <xmin>2307</xmin>
      <ymin>1271</ymin>
      <xmax>2375</xmax>
      <ymax>1339</ymax>
    </bndbox>
  </object>
  <object>
    <name>aws_amazon_route_53</name>
    <pose>Unspecified</pose>
    <truncated>0</truncated>
    <difficult>0</difficult>
    <bndbox>
      <xmin>3099</xmin>
      <ymin>2002</ymin>
      <xmax>3235</xmax>
      <ymax>2138</ymax>
    </bndbox>
  </object>
  <object>
    <name>azure_virtual_machine</name>
    <pose>Unspecified</pose>
    <truncated>0</truncated>
    <difficult>0</difficult>
    <bndbox>
      <xmin>2106</xmin>
      <ymin>404</ymin>
      <xmax>2236</xmax>
      <ymax>534</ymax>
    </bndbox>
  </object>
</annotation>
